{
  "Halo": "Hello",
  "Hai": "Hi",
  "Selamat pagi": "Good morning",
  "Selamat malam": "Good evening",
  "Selamat tinggal": "Goodbye",
  "Senang berjumpa": "Nice to meet you",
  "Apa kabar": "How are you",
  "Kabar baik": "I'm fine",
  "Lama tidak bertemu": "Long time no see",
  "Selamat datang": "Welcome",
  "Semoga harimu menyenangkan": "Have a good day",
  "Sampai jumpa": "See you again",
  "Selamat tidur": "Good night",
  "Terima kasih": "Thank you",
  "Sama-sama": "You're welcome",
  "Maaf": "I'm sorry",
  "Tidak apa-apa": "It's okay",
  "Ya": "Yes",
  "Tidak": "No",
  "Saya mengerti": "I understand",
  "Siapa nama Anda": "What's your name",
  "Anda dari mana": "Where are you from",
  "Saya dari Korea": "I'm from Korea",
  "Apakah Anda bisa bahasa Inggris": "Do you speak English",
  "Saya tidak mengerti": "I don't understand",
  "Tolong ulangi": "Please say that again",
  "Bicara pelan-pelan": "Please speak slowly",
  "Apa katamu": "What did you say",
  "Jam berapa sekarang": "What time is it",
  "Cuaca bagus hari ini": "It's nice weather today",
  "Tolong saya": "Please help me",
  "Saya lapar": "I'm hungry",
  "Saya haus": "I'm thirsty",
  "Saya lelah": "I'm tired",
  "Aku cinta kamu": "I love you",
  "Aku merindukanmu": "I miss you",
  "Selamat": "Congratulations",
  "Baik": "Good",
  "Keren": "Awesome",
  "Menyenangkan": "It's fun",
  "Cantik": "It's pretty",
  "Enak": "It's delicious",
  "Saya bahagia": "I'm happy",
  "Saya sedih": "I'm sad",
  "Saya marah": "I'm angry",
  "Saya takut": "I'm scared",
  "Luar biasa": "Amazing",
  "Tolong": "Please",
  "Air tolong": "Water please",
  "Di mana toilet": "Where is the bathroom",
  "Berapa harganya": "How much is it",
  "Minta bill": "Check please",
  "Bersulang": "Cheers",
  "Selamat ulang tahun": "Happy birthday",
  "Selamat Tahun Baru": "Happy New Year",
  "Selamat Natal": "Merry Christmas"
}