{
  "สวัสดี": "Ciao",
  "หวัดดี": "Ciao",
  "อรุณสวัสดิ์": "Buongiorno",
  "สวัสดีตอนเย็น": "Buonasera",
  "ลาก่อน": "Arrivederci",
  "ยินดีที่ได้รู้จัก": "Piacere",
  "สบายดีไหม": "Come stai",
  "สบายดี": "Sto bene",
  "ไม่ได้เจอกันนานเลย": "Da tanto tempo",
  "ยินดีต้อนรับ": "Benvenuto",
  "ขอให้มีวันที่ดี": "Buona giornata",
  "เจอกันใหม่": "A presto",
  "ราตรีสวัสดิ์": "Buonanotte",
  "ขอบคุณ": "Grazie",
  "ไม่เป็นไร": "Va bene",
  "ขอโทษ": "Mi dispiace",
  "ใช่": "Sì",
  "ไม่": "No",
  "เข้าใจแล้ว": "Capisco",
  "คุณชื่ออะไร": "Come ti chiami",
  "คุณมาจากไหน": "Di dove sei",
  "ฉันมาจากเกาหลี": "Vengo dalla Corea",
  "คุณพูดภาษาอังกฤษไหม": "Parli inglese",
  "ฉันไม่เข้าใจ": "Non capisco",
  "พูดอีกครั้งได้ไหม": "Ripeti per favore",
  "พูดช้าๆ ได้ไหม": "Parla più lentamente",
  "ว่าไงนะ": "Cosa hai detto",
  "กี่โมงแล้ว": "Che ore sono",
  "วันนี้อากาศดี": "Bel tempo oggi",
  "ช่วยด้วย": "Aiutami per favore",
  "หิวแล้ว": "Ho fame",
  "กระหายน้ำ": "Ho sete",
  "เหนื่อย": "Sono stanco",
  "ฉันรักคุณ": "Ti amo",
  "คิดถึง": "Mi manchi",
  "ยินดีด้วย": "Congratulazioni",
  "ดี": "Bene",
  "เยี่ยม": "Fantastico",
  "สนุก": "È divertente",
  "สวย": "È bello",
  "อร่อย": "È delizioso",
  "มีความสุข": "Sono felice",
  "เศร้า": "Sono triste",
  "โกรธ": "Sono arrabbiato",
  "กลัว": "Ho paura",
  "น่าทึ่ง": "Incredibile",
  "กรุณา": "Per favore",
  "ขอน้ำ": "Acqua per favore",
  "ห้องน้ำอยู่ที่ไหน": "Dov'è il bagno",
  "เท่าไหร่": "Quanto costa",
  "คิดเงิน": "Il conto per favore",
  "ชนแก้ว": "Salute",
  "สุขสันต์วันเกิด": "Buon compleanno",
  "สวัสดีปีใหม่": "Buon anno",
  "สุขสันต์วันคริสต์มาส": "Buon Natale"
}